dbartfct/__init__.py
dbartfct/plibrary.py
dbartfct-0.0.1.dist-info/METADATA
dbartfct-0.0.1.dist-info/WHEEL
dbartfct-0.0.1.dist-info/top_level.txt
dbartfct-0.0.1.dist-info/RECORD
